sponsrdump/__init__.py
sponsrdump/base.py
sponsrdump/bg.png
sponsrdump/cli.py
sponsrdump/exceptions.py
sponsrdump/utils.py
sponsrdump/converters/__init__.py
sponsrdump/converters/base.py
sponsrdump/converters/html.py
sponsrdump/converters/markdown.py
sponsrdump-0.1.3.dist-info/METADATA
sponsrdump-0.1.3.dist-info/WHEEL
sponsrdump-0.1.3.dist-info/entry_points.txt
sponsrdump-0.1.3.dist-info/RECORD
