Metadata-Version: 2.4
Name: sponsrdump
Version: 0.1.3
Summary: Make local backup copies for materials from sponsr.ru
Project-URL: Homepage, https://github.com/idlesign/sponsrdump
Author-email: Igor Starikov <idlesign@yandex.ru>
License-Expression: BSD-3-Clause
Keywords: backup
Requires-Python: >=3.11
Requires-Dist: beautifulsoup4>=4.12.2
Requires-Dist: html2text>=2020.1.16
Requires-Dist: lxml>=4.9.3
Requires-Dist: requests>=2.31.0
